pams/__init__.py
pams/agents/__init__.py
pams/agents/arbitrage_agent.py
pams/agents/base.py
pams/agents/fcn_agent.py
pams/agents/high_frequency_agent.py
pams/agents/market_maker_agent.py
pams/agents/market_share_fcn_agent.py
pams/agents/test_agent.py
pams/events/__init__.py
pams/events/base.py
pams/events/fundamental_price_shock.py
pams/events/order_mistake_shock.py
pams/events/price_limit_rule.py
pams/events/trading_halt_rule.py
pams/fundamentals.py
pams/index_market.py
pams/logs/__init__.py
pams/logs/base.py
pams/logs/market_step_loggers.py
pams/market.py
pams/order.py
pams/order_book.py
pams/runners/__init__.py
pams/runners/base.py
pams/runners/sequential.py
pams/session.py
pams/simulator.py
pams/utils/__init__.py
pams/utils/class_finder.py
pams/utils/json_extends.py
pams/utils/json_random.py
pams/version.py
pams-0.2.2.dist-info/LICENSE
pams-0.2.2.dist-info/METADATA
pams-0.2.2.dist-info/WHEEL
pams-0.2.2.dist-info/RECORD
