Metadata-Version: 2.1
Name: pams
Version: 0.2.2
Summary: PAMS: Platform for Artificial Market Simulations
License: EPL-1.0
Author: Masanori HIRANO
Author-email: masa.hirano.1996@gmail.com
Requires-Python: >=3.9,<4.0
Classifier: License :: OSI Approved :: Eclipse Public License 1.0 (EPL-1.0)
Classifier: Programming Language :: Python :: 3
Classifier: Programming Language :: Python :: 3.9
Classifier: Programming Language :: Python :: 3.10
Classifier: Programming Language :: Python :: 3.11
Classifier: Programming Language :: Python :: 3.12
Classifier: Programming Language :: Python :: 3.13
Requires-Dist: numpy (>=1.25.1,<2.0.0)
Requires-Dist: scipy (>=1.14.1,<2.0.0) ; python_version >= "3.13" and python_version < "4.0"
Requires-Dist: scipy (>=1.9.2,<2.0.0) ; python_version >= "3.8" and python_version < "3.13"
Requires-Dist: tqdm (>=4.64.1,<5.0.0)
